port_experience/__init__.py
port_experience/cli.py
port_experience/main.py
port_experience/managers/__init__.py
port_experience/managers/action_manager.py
port_experience/managers/blueprint_manager.py
port_experience/managers/blueprint_tree_manager.py
port_experience/managers/mapping_manager.py
port_experience/managers/secret_manager.py
port_experience/managers/widget_manager.py
port_experience-0.1.4.dist-info/licenses/LICENSE
port_experience-0.1.4.dist-info/METADATA
port_experience-0.1.4.dist-info/WHEEL
port_experience-0.1.4.dist-info/entry_points.txt
port_experience-0.1.4.dist-info/top_level.txt
port_experience-0.1.4.dist-info/RECORD
