Metadata-Version: 2.4
Name: port-experience
Version: 0.1.4
Summary: A Python middleware service for managing Port.io resources including blueprints, actions, mappings, and widgets
Author-email: CS - SA TEAM <cs-sa@port.io>
Maintainer-email: Erioluwa Asiru <eri.asiru@port.io>
License-Expression: MIT
Project-URL: Source Code, https://github.com/port-experimental/one-click-port-experience
Keywords: port,port.io,getport,internal-developer-portal,idp,blueprints,middleware,devops,platform-engineering
Classifier: Development Status :: 3 - Alpha
Classifier: Intended Audience :: Developers
Classifier: Topic :: Software Development :: Build Tools
Classifier: Topic :: Software Development :: Libraries :: Python Modules
Classifier: Programming Language :: Python :: 3
Classifier: Programming Language :: Python :: 3.10
Classifier: Programming Language :: Python :: 3.11
Classifier: Programming Language :: Python :: 3.12
Classifier: Operating System :: OS Independent
Requires-Python: >=3.10
License-File: LICENSE
Requires-Dist: requests>=2.31.0
Requires-Dist: click>=8.0.0
Provides-Extra: dev
Requires-Dist: pytest>=7.0.0; extra == "dev"
Requires-Dist: black>=23.0.0; extra == "dev"
Requires-Dist: flake8>=6.0.0; extra == "dev"
Requires-Dist: mypy>=1.0.0; extra == "dev"
Dynamic: license-file
